mosart/__init__.py
mosart/lsquares.py
mosart/sfs.py
mosart-1.0.2.dist-info/licenses/LICENSE
mosart-1.0.2.dist-info/METADATA
mosart-1.0.2.dist-info/WHEEL
mosart-1.0.2.dist-info/top_level.txt
mosart-1.0.2.dist-info/RECORD
