Metadata-Version: 2.4
Name: mosart
Version: 1.0.2
Summary: Morphology from SAR tool
Author-email: Mario Angarita Vargas <mfangaritasr@alaska.edu>, Ronni Grapenthin <rgrapenthin@alaska.edu>, Franz Meyer <fjmeyer@alaska.edu>, Simon Plank <simon.Plank@dlr.de>, Michael Christoffersen <mchristoffersen@alaska.edu>
License: MIT License
Project-URL: documentation, https://github.com/mfangaritav/MOSART
Project-URL: repository, https://github.com/mfangaritav/MOSART
Requires-Python: >=3.8
License-File: LICENSE
Requires-Dist: asf_search>=6.4.0
Requires-Dist: h5py==3.*
Requires-Dist: gdal
Requires-Dist: matplotlib==3.*
Requires-Dist: numpy==1.*
Requires-Dist: scipy==1.*
Requires-Dist: scikit-image==0.22.0
Requires-Dist: utm==0.7.0
Dynamic: license-file
